{
  "id": "320071be-4196-402b-98d7-d34bec8a1aab",
  "title": "Death Note",
  "type_id": "106f524e-7283-44b8-aa84-25e9a7fb1f7d",
  "tasks": [
    {
      "id": "63698905-4149-434a-abfd-59e2343c1c07",
      "series_id": "320071be-4196-402b-98d7-d34bec8a1aab",
      "author_id": "17491b54-580f-4d5f-94e5-9b9e501871c4",
      "job_id": "bf39f3fe-ce75-48b0-b557-877da935633b",
      "author": {
        "id": "17491b54-580f-4d5f-94e5-9b9e501871c4",
        "name": "Ōba",
        "first_name": "Tsugumi"
      }
    },
    {
      "id": "adb8225f-c8ee-41cc-9d14-2dd0b663a6cf",
      "series_id": "320071be-4196-402b-98d7-d34bec8a1aab",
      "author_id": "f06df71d-7bb3-4a4c-aec0-638f53aa43a8",
      "job_id": "37fb2477-ec0d-4ffc-9d3b-4189c2d01629",
      "author": {
        "id": "f06df71d-7bb3-4a4c-aec0-638f53aa43a8",
        "name": "Obata",
        "first_name": "Takeshi"
      }
    }
  ],
  "editions": [
    {
      "id": "908612fd-1cc7-4780-aea4-63d3ac04c6bd",
      "title": "Black Edition",
      "series_id": "320071be-4196-402b-98d7-d34bec8a1aab",
      "publisher_id": "4c9547ff-2ef6-439a-80b8-ea705a385b76",
      "volumes": [
        {
          "id": "ec9d0282-78a1-491e-bd1e-a937b332c56f",
          "title": "Tome 6",
          "number": 6,
          "date": "2011-05-06",
          "img": "https://images-eu.ssl-images-amazon.com/images/I/41FBONjMi4L.jpg",
          "edition_id": "908612fd-1cc7-4780-aea4-63d3ac04c6bd",
          "isbn": "9782505010951"
        },
        {
          "id": "ef282203-2ef5-4972-9598-d365fe7ff09c",
          "title": "Tome 5",
          "number": 5,
          "date": "2011-03-04",
          "img": "https://images-eu.ssl-images-amazon.com/images/I/41%2BDT%2B3-rwL.jpg",
          "edition_id": "908612fd-1cc7-4780-aea4-63d3ac04c6bd",
          "isbn": "9782505010692"
        },
        {
          "id": "69fed8ee-a500-4bde-9ba2-458f639785d1",
          "title": "Tome 4",
          "number": 4,
          "date": "2011-01-07",
          "img": "https://images-eu.ssl-images-amazon.com/images/I/41lRggimfJL.jpg",
          "edition_id": "908612fd-1cc7-4780-aea4-63d3ac04c6bd",
          "isbn": "9782505010326"
        },
        {
          "id": "7ac3f560-bb02-4a9e-9e01-67cc2e2b9d32",
          "title": "Tome 3",
          "number": 3,
          "date": "2010-11-05",
          "img": "https://images-eu.ssl-images-amazon.com/images/I/41mLoqm6D0L.jpg",
          "edition_id": "908612fd-1cc7-4780-aea4-63d3ac04c6bd",
          "isbn": "9782505009986"
        },
        {
          "id": "3a03733c-1a5a-4673-9299-28e5cc82a8af",
          "title": "Tome 2",
          "number": 2,
          "date": "2010-09-03",
          "img": "https://images-eu.ssl-images-amazon.com/images/I/51KMP3phtGL.jpg",
          "edition_id": "908612fd-1cc7-4780-aea4-63d3ac04c6bd",
          "isbn": "9782505009061"
        },
        {
          "id": "dbab2483-2d3c-4832-9993-b6efbd765787",
          "title": "Tome 1",
          "number": 1,
          "date": "2010-07-02",
          "img": "https://images-eu.ssl-images-amazon.com/images/I/413rEPunmPL.jpg",
          "edition_id": "908612fd-1cc7-4780-aea4-63d3ac04c6bd",
          "isbn": "9782505009054"
        }
      ]
    },
    {
      "id": "5482eba9-2773-40d8-82f7-1870b1b2a3e9",
      "title": "Edition simple",
      "series_id": "320071be-4196-402b-98d7-d34bec8a1aab",
      "publisher_id": "4c9547ff-2ef6-439a-80b8-ea705a385b76",
      "volumes": [
        {
          "id": "081648ff-1b14-4af7-b8f0-9e97b0ba6804",
          "title": "Tome 13",
          "number": 13,
          "date": "2009-09-18",
          "img": "https://images-eu.ssl-images-amazon.com/images/I/51JrRDR1ANL.jpg",
          "edition_id": "5482eba9-2773-40d8-82f7-1870b1b2a3e9",
          "isbn": "9782505004523"
        },
        {
          "id": "11606764-7aee-4e33-9df1-e9dc5298eda8",
          "title": "Tome 12",
          "number": 12,
          "date": "2008-10-02",
          "img": "https://images-eu.ssl-images-amazon.com/images/I/61XFUTPtQdL.jpg",
          "edition_id": "5482eba9-2773-40d8-82f7-1870b1b2a3e9",
          "isbn": "9782505004295"
        },
        {
          "id": "a4477f49-cff1-4913-bd39-68fefbc10479",
          "title": "Tome 11",
          "number": 11,
          "date": "2008-07-04",
          "img": "https://images-eu.ssl-images-amazon.com/images/I/618b1GXgGFL.jpg",
          "edition_id": "5482eba9-2773-40d8-82f7-1870b1b2a3e9",
          "isbn": "9782505003694"
        },
        {
          "id": "c1995831-6447-43e9-869b-74f2cf93966d",
          "title": "Tome 10",
          "number": 10,
          "date": "2008-06-06",
          "img": "https://images-eu.ssl-images-amazon.com/images/I/61OEH0gsrIL.jpg",
          "edition_id": "5482eba9-2773-40d8-82f7-1870b1b2a3e9",
          "isbn": "9782505003038"
        },
        {
          "id": "73f6690b-716b-4659-97f5-d66ce10acd8a",
          "title": "Tome 9",
          "number": 9,
          "date": "2008-04-11",
          "img": "https://images-eu.ssl-images-amazon.com/images/I/61jqfMbZ8VL.jpg",
          "edition_id": "5482eba9-2773-40d8-82f7-1870b1b2a3e9",
          "isbn": "9782505002970"
        },
        {
          "id": "12b5dc0d-253a-41dd-bbee-e1f31e947eb1",
          "title": "Tome 8",
          "number": 8,
          "date": "2008-02-15",
          "img": "https://images-eu.ssl-images-amazon.com/images/I/51ZlUQFdaPL.jpg",
          "edition_id": "5482eba9-2773-40d8-82f7-1870b1b2a3e9",
          "isbn": "9782505002697"
        },
        {
          "id": "f0bc0f76-bddf-4af8-a589-0d877aae9235",
          "title": "Tome 7",
          "number": 7,
          "date": "2007-12-07",
          "img": "https://images-eu.ssl-images-amazon.com/images/I/61qgonxtZOL.jpg",
          "edition_id": "5482eba9-2773-40d8-82f7-1870b1b2a3e9",
          "isbn": "9782505001997"
        },
        {
          "id": "a2280876-7082-48b5-bab3-34c4e5eab279",
          "title": "Tome 6",
          "number": 6,
          "date": "2007-10-05",
          "img": "https://images-eu.ssl-images-amazon.com/images/I/51ccrw7ky1L.jpg",
          "edition_id": "5482eba9-2773-40d8-82f7-1870b1b2a3e9",
          "isbn": "9782505001812"
        },
        {
          "id": "b95ab092-9baf-4feb-b8f1-e79b449b9c54",
          "title": "Tome 5",
          "number": 5,
          "date": "2007-08-24",
          "img": "https://images-eu.ssl-images-amazon.com/images/I/61bXKQlOllL.jpg",
          "edition_id": "5482eba9-2773-40d8-82f7-1870b1b2a3e9",
          "isbn": "9782505001614"
        },
        {
          "id": "e7dbccb5-4710-446b-8c08-d35fb8a1eaeb",
          "title": "Tome 4",
          "number": 4,
          "date": "2007-05-31",
          "img": "https://images-eu.ssl-images-amazon.com/images/I/611d8aPhqhL.jpg",
          "edition_id": "5482eba9-2773-40d8-82f7-1870b1b2a3e9",
          "isbn": "9782505001065"
        },
        {
          "id": "fa7a1162-d9e3-462f-a367-8371a55f7c94",
          "title": "Tome 3",
          "number": 3,
          "date": "2007-04-05",
          "img": "https://images-eu.ssl-images-amazon.com/images/I/61fiEjVbUbL.jpg",
          "edition_id": "5482eba9-2773-40d8-82f7-1870b1b2a3e9",
          "isbn": "9782505000792"
        },
        {
          "id": "11d1491e-22d4-49f1-b29f-78007493d4e6",
          "title": "Tome 2",
          "number": 2,
          "date": "2007-02-01",
          "img": "https://images-eu.ssl-images-amazon.com/images/I/61DduSmdKGL.jpg",
          "edition_id": "5482eba9-2773-40d8-82f7-1870b1b2a3e9",
          "isbn": "9782505000426"
        },
        {
          "id": "ff15ae7e-fcfe-4061-a27b-3b481e5f313c",
          "title": "Tome 1",
          "number": 1,
          "date": "2007-01-18",
          "img": "https://images-eu.ssl-images-amazon.com/images/I/51eBp6XUd5L.jpg",
          "edition_id": "5482eba9-2773-40d8-82f7-1870b1b2a3e9",
          "isbn": "9782505000327"
        }
      ]
    }
  ],
  "kinds": [
    {
      "id": "9d6a131c-4b4e-4cf6-a9aa-de78087d672d",
      "title": "Fantastique"
    },
    {
      "id": "c67e1d91-20c3-43b6-98da-aea886176da0",
      "title": "Gothique"
    },
    {
      "id": "eb5eb1b3-9f89-43ab-b0fa-0ef61f10d633",
      "title": "Enquête"
    },
    {
      "id": "acd6bec9-507d-46ab-a1de-f18f8b8ca83c",
      "title": "Drame"
    },
    {
      "id": "20840e27-413b-47c1-83f3-042be2c5ff0d",
      "title": "Dieu et Déesse"
    },
    {
      "id": "5faba927-085f-4fbd-a468-4456352ba872",
      "title": "Psychologique"
    },
    {
      "id": "d806ffd0-c43e-4e78-a557-8d7b41cc44e2",
      "title": "Assassin"
    },
    {
      "id": "eb84f0d1-680d-4127-a416-3bb78c365d9d",
      "title": "Agent secret"
    },
    {
      "id": "e0919979-ca6f-4025-ba1d-9897d5f075d4",
      "title": "Thriller"
    },
    {
      "id": "d5a3385a-cfcd-45f6-8f82-0c80956b084d",
      "title": "Shōnen"
    },
    {
      "id": "fa3722c2-f18c-480e-bd4d-e915de81e69d",
      "title": "Policier"
    }
  ]
}